shexviz/__init__.py
shexviz/__main__.py
shexviz/shex2dot.py
shexviz-0.1.2.dist-info/LICENSE
shexviz-0.1.2.dist-info/METADATA
shexviz-0.1.2.dist-info/WHEEL
shexviz-0.1.2.dist-info/entry_points.txt
shexviz-0.1.2.dist-info/top_level.txt
shexviz-0.1.2.dist-info/RECORD
