Metadata-Version: 2.1
Name: shexviz
Version: 0.1.2
Summary: Visualize ShEx shapes
Author-email: Andra Waagmeester <andra@micelio.be>
License: MIT License
Project-URL: Homepage, https://github.com/micelio/shexviz
Keywords: shex,dot,graphviz
Classifier: License :: OSI Approved :: MIT License
Classifier: Programming Language :: Python
Classifier: Programming Language :: Python :: 3
Requires-Python: >=3.8
License-File: LICENSE
Requires-Dist: ShExJSG
Requires-Dist: pyshex
Requires-Dist: graphviz
